make_stubs.py
stubmaker/__init__.py
stubmaker/builder/__init__.py
stubmaker/builder/common.py
stubmaker/builder/import_.py
stubmaker/builder/representations_tree_builder.py
stubmaker/builder/definitions/__init__.py
stubmaker/builder/definitions/attribute_annotation_def.py
stubmaker/builder/definitions/attribute_def.py
stubmaker/builder/definitions/base_class_def.py
stubmaker/builder/definitions/class_def.py
stubmaker/builder/definitions/documentation_def.py
stubmaker/builder/definitions/enum_def.py
stubmaker/builder/definitions/function_def.py
stubmaker/builder/definitions/metaclass_def.py
stubmaker/builder/definitions/module_def.py
stubmaker/builder/literals/__init__.py
stubmaker/builder/literals/enum_value_literal.py
stubmaker/builder/literals/reference_literal.py
stubmaker/builder/literals/type_hint_literal.py
stubmaker/builder/literals/type_var_literal.py
stubmaker/builder/literals/value_literal.py
stubmaker/viewers/__init__.py
stubmaker/viewers/basic_viewer.py
stubmaker/viewers/common.py
stubmaker/viewers/markdown_viewer.py
stubmaker/viewers/stub_viewer.py
stubmaker/viewers/util.py
stubmaker-0.1.0.dist-info/AUTHORS
stubmaker-0.1.0.dist-info/LICENSE
stubmaker-0.1.0.dist-info/METADATA
stubmaker-0.1.0.dist-info/WHEEL
stubmaker-0.1.0.dist-info/entry_points.txt
stubmaker-0.1.0.dist-info/top_level.txt
stubmaker-0.1.0.dist-info/RECORD
