Metadata-Version: 2.1
Name: stubmaker
Version: 0.1.0
Summary: Tool for generating python stubs
Author-email: Vladimir Losev <losev@yandex-team.ru>
Requires-Python: <3.12,>=3.7.4
License-File: LICENSE
License-File: AUTHORS
Requires-Dist: docstring-parser
Requires-Dist: typing-inspect
Requires-Dist: markdown-it-py
